guardify/__init__.py
guardify/authority.py
guardify/errors.py
guardify/py.typed
guardify/token.py
guardify-0.4.0.dist-info/LICENSE
guardify-0.4.0.dist-info/METADATA
guardify-0.4.0.dist-info/WHEEL
guardify-0.4.0.dist-info/top_level.txt
guardify-0.4.0.dist-info/RECORD
