Metadata-Version: 2.1
Name: guardify
Version: 0.4.0
Summary: A simple library for token generation and validation.
Maintainer-email: Nadav Tasher <hey@nadav.app>
License: MIT License
Project-URL: Homepage, https://github.com/NadavTasher/Guardify
Keywords: token,authentication
Classifier: License :: OSI Approved :: MIT License
Classifier: Programming Language :: Python :: 3
License-File: LICENSE
Requires-Dist: runtypes ~=0.6.2
